{"001-3.jpg257790":{"filename":"001-3.jpg","size":257790,"regions":[{"shape_attributes":{"name":"polygon","all_points_x":[267,365,346,318,195,197],"all_points_y":[691,607,580,513,570,611]},"region_attributes":{"Cervical spine":{"1":true}}},{"shape_attributes":{"name":"polygon","all_points_x":[287,287,349,435,398,385,373],"all_points_y":[699,679,631,705,738,800,802]},"region_attributes":{"Cervical spine":{"2":true}}},{"shape_attributes":{"name":"polygon","all_points_x":[398,398,449,504,531,490,459],"all_points_y":[818,791,715,767,783,818,884]},"region_attributes":{"Cervical spine":{"3":true}}},{"shape_attributes":{"name":"polygon","all_points_x":[467,541,613,558,517],"all_points_y":[890,802,875,908,970]},"region_attributes":{"Cervical spine":{"4":true}}},{"shape_attributes":{"name":"polygon","all_points_x":[525,615,681,588,576],"all_points_y":[982,890,968,1041,1050]},"region_attributes":{"Cervical spine":{"5":true}}},{"shape_attributes":{"name":"polygon","all_points_x":[580,676,726,636],"all_points_y":[1058,992,1068,1127]},"region_attributes":{"Cervical spine":{"6":true}}},{"shape_attributes":{"name":"polygon","all_points_x":[638,734,783,681],"all_points_y":[1138,1074,1158,1228]},"region_attributes":{"Cervical spine":{"7":true}}}],"file_attributes":{}},"001-4.jpg303887":{"filename":"001-4.jpg","size":303887,"regions":[{"shape_attributes":{"name":"polygon","all_points_x":[707,674,601,681,771],"all_points_y":[513,515,584,687,658]},"region_attributes":{"Cervical spine":{"1":true}}},{"shape_attributes":{"name":"polygon","all_points_x":[574,652,605,554,498],"all_points_y":[607,652,767,736,724]},"region_attributes":{"Cervical spine":{"2":true}}},{"shape_attributes":{"name":"polygon","all_points_x":[482,582,553,496,431],"all_points_y":[754,771,871,841,841]},"region_attributes":{"Cervical spine":{"3":true}}},{"shape_attributes":{"name":"polygon","all_points_x":[414,537,517,467,400,394],"all_points_y":[875,873,970,953,963,951]},"region_attributes":{"Cervical spine":{"4":true}}},{"shape_attributes":{"name":"polygon","all_points_x":[385,502,521,455,396],"all_points_y":[998,966,1048,1058,1084]},"region_attributes":{"Cervical spine":{"5":true}}},{"shape_attributes":{"name":"polygon","all_points_x":[389,498,521,431],"all_points_y":[1115,1064,1156,1197]},"region_attributes":{"Cervical spine":{"6":true}}},{"shape_attributes":{"name":"polygon","all_points_x":[435,525,554,455],"all_points_y":[1205,1160,1236,1298]},"region_attributes":{"Cervical spine":{"7":true}}}],"file_attributes":{}},"002-3.jpg273687":{"filename":"002-3.jpg","size":273687,"regions":[{"shape_attributes":{"name":"polygon","all_points_x":[309,337,462,451],"all_points_y":[381,504,478,357]},"region_attributes":{"Cervical spine":{"1":true}}},{"shape_attributes":{"name":"polygon","all_points_x":[341,459,485,440,411,385],"all_points_y":[549,497,603,625,661,653]},"region_attributes":{"Cervical spine":{"2":true}}},{"shape_attributes":{"name":"polygon","all_points_x":[411,491,549,499,464,437],"all_points_y":[677,613,702,726,768,732]},"region_attributes":{"Cervical spine":{"3":true}}},{"shape_attributes":{"name":"polygon","all_points_x":[472,565,589,609,552,517],"all_points_y":[779,710,782,820,836,873]},"region_attributes":{"Cervical spine":{"4":true}}},{"shape_attributes":{"name":"polygon","all_points_x":[537,614,638,664,619,571],"all_points_y":[888,833,884,918,939,974]},"region_attributes":{"Cervical spine":{"5":true}}},{"shape_attributes":{"name":"polygon","all_points_x":[576,681,697,710,641,585],"all_points_y":[992,936,990,1025,1035,1064]},"region_attributes":{"Cervical spine":{"6":true}}},{"shape_attributes":{"name":"polygon","all_points_x":[604,708,728,637,623],"all_points_y":[1081,1035,1129,1185,1163]},"region_attributes":{"Cervical spine":{"7":true}}}],"file_attributes":{}},"002-4.jpg304592":{"filename":"002-4.jpg","size":304592,"regions":[{"shape_attributes":{"name":"polygon","all_points_x":[443,369,469,549],"all_points_y":[347,453,517,440]},"region_attributes":{"Cervical spine":{"1":true}}},{"shape_attributes":{"name":"polygon","all_points_x":[325,453,417,363,317,304],"all_points_y":[485,523,622,606,614,579]},"region_attributes":{"Cervical spine":{"2":true}}},{"shape_attributes":{"name":"polygon","all_points_x":[309,403,398,347,301,293],"all_points_y":[643,633,739,726,740,716]},"region_attributes":{"Cervical spine":{"3":true}}},{"shape_attributes":{"name":"polygon","all_points_x":[293,389,406,350,309],"all_points_y":[769,744,852,856,878]},"region_attributes":{"Cervical spine":{"4":true}}},{"shape_attributes":{"name":"polygon","all_points_x":[321,405,445,382,352],"all_points_y":[907,867,950,968,1003]},"region_attributes":{"Cervical spine":{"5":true}}},{"shape_attributes":{"name":"polygon","all_points_x":[365,456,494,430,381],"all_points_y":[1027,963,1044,1060,1096]},"region_attributes":{"Cervical spine":{"6":true}}},{"shape_attributes":{"name":"polygon","all_points_x":[406,499,512,537,481,453,430],"all_points_y":[1113,1064,1105,1150,1171,1204,1188]},"region_attributes":{"Cervical spine":{"7":true}}}],"file_attributes":{}},"003-3.jpg281593":{"filename":"003-3.jpg","size":281593,"regions":[{"shape_attributes":{"name":"polygon","all_points_x":[347,544,545,400],"all_points_y":[385,344,485,526]},"region_attributes":{"Cervical spine":{"1":true}}},{"shape_attributes":{"name":"polygon","all_points_x":[430,555,597,544,494],"all_points_y":[537,488,616,632,686]},"region_attributes":{"Cervical spine":{"2":true}}},{"shape_attributes":{"name":"polygon","all_points_x":[504,600,649,584,528],"all_points_y":[704,641,745,768,814]},"region_attributes":{"Cervical spine":{"3":true}}},{"shape_attributes":{"name":"polygon","all_points_x":[542,662,686,627,584],"all_points_y":[849,772,878,904,947]},"region_attributes":{"Cervical spine":{"4":true}}},{"shape_attributes":{"name":"polygon","all_points_x":[598,705,745,677,625],"all_points_y":[974,888,990,1012,1062]},"region_attributes":{"Cervical spine":{"5":true}}},{"shape_attributes":{"name":"polygon","all_points_x":[635,766,779,801,732,670],"all_points_y":[1089,993,1070,1100,1128,1169]},"region_attributes":{"Cervical spine":{"6":true}}},{"shape_attributes":{"name":"polygon","all_points_x":[686,809,844,721],"all_points_y":[1190,1128,1233,1295]},"region_attributes":{"Cervical spine":{"7":true}}}],"file_attributes":{}},"003-4.jpg302117":{"filename":"003-4.jpg","size":302117,"regions":[{"shape_attributes":{"name":"polygon","all_points_x":[657,806,766,616],"all_points_y":[315,397,493,469]},"region_attributes":{"Cervical spine":{"1":true}}},{"shape_attributes":{"name":"polygon","all_points_x":[638,780,731,677,606],"all_points_y":[489,510,645,625,645]},"region_attributes":{"Cervical spine":{"2":true}}},{"shape_attributes":{"name":"polygon","all_points_x":[606,737,708,646,566],"all_points_y":[664,677,782,772,769]},"region_attributes":{"Cervical spine":{"3":true}}},{"shape_attributes":{"name":"polygon","all_points_x":[552,718,675,613,545],"all_points_y":[809,793,915,891,916]},"region_attributes":{"Cervical spine":{"4":true}}},{"shape_attributes":{"name":"polygon","all_points_x":[550,688,667,595,526],"all_points_y":[944,926,1030,1024,1040]},"region_attributes":{"Cervical spine":{"5":true}}},{"shape_attributes":{"name":"polygon","all_points_x":[539,665,664,581,517,523],"all_points_y":[1070,1057,1147,1156,1175,1108]},"region_attributes":{"Cervical spine":{"6":true}}},{"shape_attributes":{"name":"polygon","all_points_x":[529,664,669,598,542],"all_points_y":[1207,1180,1289,1300,1315]},"region_attributes":{"Cervical spine":{"7":true}}}],"file_attributes":{}},"004-3.jpg294491":{"filename":"004-3.jpg","size":294491,"regions":[{"shape_attributes":{"name":"polygon","all_points_x":[173,310,363,341,248],"all_points_y":[515,440,542,577,629]},"region_attributes":{"Cervical spine":{"1":true}}},{"shape_attributes":{"name":"polygon","all_points_x":[257,373,465,408,384,321],"all_points_y":[646,568,672,740,801,753]},"region_attributes":{"Cervical spine":{"2":true}}},{"shape_attributes":{"name":"polygon","all_points_x":[400,483,579,529,485],"all_points_y":[804,702,792,832,912]},"region_attributes":{"Cervical spine":{"3":true}}},{"shape_attributes":{"name":"polygon","all_points_x":[494,584,677,608,582],"all_points_y":[929,816,913,968,1019]},"region_attributes":{"Cervical spine":{"4":true}}},{"shape_attributes":{"name":"polygon","all_points_x":[592,673,771,712,664,635],"all_points_y":[1028,939,1025,1073,1148,1084]},"region_attributes":{"Cervical spine":{"5":true}}},{"shape_attributes":{"name":"polygon","all_points_x":[669,771,852,787,747,713],"all_points_y":[1163,1054,1156,1206,1259,1195]},"region_attributes":{"Cervical spine":{"6":true}}},{"shape_attributes":{"name":"polygon","all_points_x":[755,865,942,824,785],"all_points_y":[1278,1172,1279,1374,1303]},"region_attributes":{"Cervical spine":{"7":true}}}],"file_attributes":{}},"004-4.jpg309295":{"filename":"004-4.jpg","size":309295,"regions":[{"shape_attributes":{"name":"polygon","all_points_x":[400,550,569,432],"all_points_y":[352,350,478,507]},"region_attributes":{"Cervical spine":{"1":true}}},{"shape_attributes":{"name":"polygon","all_points_x":[433,585,603,545,486,443],"all_points_y":[531,494,645,657,716,616]},"region_attributes":{"Cervical spine":{"2":true}}},{"shape_attributes":{"name":"polygon","all_points_x":[494,609,677,603,549],"all_points_y":[737,664,769,808,867]},"region_attributes":{"Cervical spine":{"3":true}}},{"shape_attributes":{"name":"polygon","all_points_x":[560,686,728,657,613],"all_points_y":[876,811,926,955,1001]},"region_attributes":{"Cervical spine":{"4":true}}},{"shape_attributes":{"name":"polygon","all_points_x":[621,729,792,712,648,641],"all_points_y":[1012,944,1059,1096,1150,1067]},"region_attributes":{"Cervical spine":{"5":true}}},{"shape_attributes":{"name":"polygon","all_points_x":[657,787,840,761,704,692],"all_points_y":[1164,1083,1204,1236,1281,1211]},"region_attributes":{"Cervical spine":{"6":true}}},{"shape_attributes":{"name":"polygon","all_points_x":[704,840,891,744,731],"all_points_y":[1302,1235,1345,1409,1335]},"region_attributes":{"Cervical spine":{"7":true}}}],"file_attributes":{}},"006-3.jpg269199":{"filename":"006-3.jpg","size":269199,"regions":[{"shape_attributes":{"name":"polygon","all_points_x":[374,381,477,485],"all_points_y":[593,675,672,574]},"region_attributes":{"Cervical spine":{"1":true}}},{"shape_attributes":{"name":"polygon","all_points_x":[382,453,504,446],"all_points_y":[721,677,792,830]},"region_attributes":{"Cervical spine":{"2":true}}},{"shape_attributes":{"name":"polygon","all_points_x":[457,509,569,523],"all_points_y":[836,800,868,904]},"region_attributes":{"Cervical spine":{"3":true}}},{"shape_attributes":{"name":"polygon","all_points_x":[533,584,657,613],"all_points_y":[916,870,934,985]},"region_attributes":{"Cervical spine":{"4":true}}},{"shape_attributes":{"name":"polygon","all_points_x":[632,675,744,696],"all_points_y":[993,931,985,1051]},"region_attributes":{"Cervical spine":{"5":true}}},{"shape_attributes":{"name":"polygon","all_points_x":[712,769,840,795,779],"all_points_y":[1054,987,1051,1086,1121]},"region_attributes":{"Cervical spine":{"6":true}}},{"shape_attributes":{"name":"polygon","all_points_x":[793,856,928,878,856],"all_points_y":[1128,1054,1143,1171,1206]},"region_attributes":{"Cervical spine":{"7":true}}}],"file_attributes":{}},"006-4.jpg273746":{"filename":"006-4.jpg","size":273746,"regions":[{"shape_attributes":{"name":"polygon","all_points_x":[584,549,659,680],"all_points_y":[520,625,632,545]},"region_attributes":{"Cervical spine":{"1":true}}},{"shape_attributes":{"name":"polygon","all_points_x":[549,645,645,568],"all_points_y":[646,645,748,763]},"region_attributes":{"Cervical spine":{"2":true}}},{"shape_attributes":{"name":"polygon","all_points_x":[576,641,680,616],"all_points_y":[782,756,838,865]},"region_attributes":{"Cervical spine":{"3":true}}},{"shape_attributes":{"name":"polygon","all_points_x":[638,688,744,681],"all_points_y":[881,846,928,966]},"region_attributes":{"Cervical spine":{"4":true}}},{"shape_attributes":{"name":"polygon","all_points_x":[694,750,814,744],"all_points_y":[977,932,1008,1059]},"region_attributes":{"Cervical spine":{"5":true}}},{"shape_attributes":{"name":"polygon","all_points_x":[761,833,883,812],"all_points_y":[1065,1022,1104,1153]},"region_attributes":{"Cervical spine":{"6":true}}},{"shape_attributes":{"name":"polygon","all_points_x":[817,899,944,851],"all_points_y":[1158,1108,1214,1257]},"region_attributes":{"Cervical spine":{"7":true}}}],"file_attributes":{}},"007-3.jpg297054":{"filename":"007-3.jpg","size":297054,"regions":[{"shape_attributes":{"name":"polygon","all_points_x":[558,694,689,582],"all_points_y":[331,296,413,427]},"region_attributes":{"Cervical spine":{"1":true}}},{"shape_attributes":{"name":"polygon","all_points_x":[585,673,704,648,603],"all_points_y":[457,433,553,569,603]},"region_attributes":{"Cervical spine":{"2":true}}},{"shape_attributes":{"name":"polygon","all_points_x":[609,708,732,667,632],"all_points_y":[621,579,667,683,712]},"region_attributes":{"Cervical spine":{"3":true}}},{"shape_attributes":{"name":"polygon","all_points_x":[641,731,766,694,664],"all_points_y":[731,683,768,798,820]},"region_attributes":{"Cervical spine":{"4":true}}},{"shape_attributes":{"name":"polygon","all_points_x":[669,766,795,721,692],"all_points_y":[846,792,875,907,923]},"region_attributes":{"Cervical spine":{"5":true}}},{"shape_attributes":{"name":"polygon","all_points_x":[704,795,820,774,728],"all_points_y":[945,897,985,1000,1025]},"region_attributes":{"Cervical spine":{"6":true}}},{"shape_attributes":{"name":"polygon","all_points_x":[742,836,870,776],"all_points_y":[1048,993,1076,1115]},"region_attributes":{"Cervical spine":{"7":true}}}],"file_attributes":{}},"007-4.jpg307954":{"filename":"007-4.jpg","size":307954,"regions":[{"shape_attributes":{"name":"polygon","all_points_x":[748,852,777,683],"all_points_y":[329,416,497,425]},"region_attributes":{"Cervical spine":{"1":true}}},{"shape_attributes":{"name":"polygon","all_points_x":[672,756,708,648,603,645],"all_points_y":[464,496,609,579,574,507]},"region_attributes":{"Cervical spine":{"2":true}}},{"shape_attributes":{"name":"polygon","all_points_x":[584,691,657,606,555],"all_points_y":[603,622,708,688,689]},"region_attributes":{"Cervical spine":{"3":true}}},{"shape_attributes":{"name":"polygon","all_points_x":[539,648,641,574,529],"all_points_y":[724,721,812,800,808]},"region_attributes":{"Cervical spine":{"4":true}}},{"shape_attributes":{"name":"polygon","all_points_x":[521,627,632,571,520],"all_points_y":[843,824,920,910,929]},"region_attributes":{"Cervical spine":{"5":true}}},{"shape_attributes":{"name":"polygon","all_points_x":[523,630,638,581,525],"all_points_y":[952,926,1011,1024,1038]},"region_attributes":{"Cervical spine":{"6":true}}},{"shape_attributes":{"name":"polygon","all_points_x":[541,638,662,565,539],"all_points_y":[1060,1025,1102,1143,1070]},"region_attributes":{"Cervical spine":{"7":true}}}],"file_attributes":{}},"008-3.jpg270657":{"filename":"008-3.jpg","size":270657,"regions":[{"shape_attributes":{"name":"polygon","all_points_x":[387,456,515,456],"all_points_y":[632,696,603,561]},"region_attributes":{"Cervical spine":{"1":true}}},{"shape_attributes":{"name":"polygon","all_points_x":[549,473,501,600],"all_points_y":[603,637,739,702]},"region_attributes":{"Cervical spine":{"2":true}}},{"shape_attributes":{"name":"polygon","all_points_x":[510,598,622,542],"all_points_y":[748,712,798,838]},"region_attributes":{"Cervical spine":{"3":true}}},{"shape_attributes":{"name":"polygon","all_points_x":[553,625,664,569,552],"all_points_y":[838,806,880,923,854]},"region_attributes":{"Cervical spine":{"4":true}}},{"shape_attributes":{"name":"polygon","all_points_x":[597,678,705,728,657,635],"all_points_y":[940,886,932,961,1000,1017]},"region_attributes":{"Cervical spine":{"5":true}}},{"shape_attributes":{"name":"polygon","all_points_x":[677,744,796,699,673],"all_points_y":[1009,961,1022,1084,1033]},"region_attributes":{"Cervical spine":{"6":true}}},{"shape_attributes":{"name":"polygon","all_points_x":[728,813,863,760,750],"all_points_y":[1108,1034,1116,1174,1140]},"region_attributes":{"Cervical spine":{"7":true}}}],"file_attributes":{}},"008-4.jpg277118":{"filename":"008-4.jpg","size":277118,"regions":[{"shape_attributes":{"name":"polygon","all_points_x":[830,804,913,929],"all_points_y":[488,566,598,518]},"region_attributes":{"Cervical spine":{"1":true}}},{"shape_attributes":{"name":"polygon","all_points_x":[782,822,852,920,923,870],"all_points_y":[646,661,700,632,601,565]},"region_attributes":{"Cervical spine":{"2":true}}},{"shape_attributes":{"name":"polygon","all_points_x":[774,848,788,718],"all_points_y":[651,705,772,712]},"region_attributes":{"Cervical spine":{"3":true}}},{"shape_attributes":{"name":"polygon","all_points_x":[716,787,750,659],"all_points_y":[732,777,849,788]},"region_attributes":{"Cervical spine":{"4":true}}},{"shape_attributes":{"name":"polygon","all_points_x":[648,736,702,635,600],"all_points_y":[816,854,929,894,897]},"region_attributes":{"Cervical spine":{"5":true}}},{"shape_attributes":{"name":"polygon","all_points_x":[622,710,692,582,600,597],"all_points_y":[929,945,1022,996,968,937]},"region_attributes":{"Cervical spine":{"6":true}}},{"shape_attributes":{"name":"polygon","all_points_x":[589,686,683,573],"all_points_y":[1040,1035,1126,1115]},"region_attributes":{"Cervical spine":{"7":true}}}],"file_attributes":{}},"009-3.jpg306473":{"filename":"009-3.jpg","size":306473,"regions":[{"shape_attributes":{"name":"polygon","all_points_x":[309,406,469,363],"all_points_y":[336,286,382,449]},"region_attributes":{"Cervical spine":{"1":true}}},{"shape_attributes":{"name":"polygon","all_points_x":[349,472,502,446,401],"all_points_y":[481,422,547,571,622]},"region_attributes":{"Cervical spine":{"2":true}}},{"shape_attributes":{"name":"polygon","all_points_x":[429,523,577,520,478,429],"all_points_y":[622,561,675,696,744,649]},"region_attributes":{"Cervical spine":{"3":true}}},{"shape_attributes":{"name":"polygon","all_points_x":[501,603,645,581,536,494],"all_points_y":[740,686,795,816,865,763]},"region_attributes":{"Cervical spine":{"4":true}}},{"shape_attributes":{"name":"polygon","all_points_x":[565,664,702,600,574,555],"all_points_y":[864,816,905,969,912,881]},"region_attributes":{"Cervical spine":{"5":true}}},{"shape_attributes":{"name":"polygon","all_points_x":[619,734,764,702,645,638],"all_points_y":[996,936,1054,1075,1105,1054]},"region_attributes":{"Cervical spine":{"6":true}}},{"shape_attributes":{"name":"polygon","all_points_x":[657,771,796,814,732,692,683],"all_points_y":[1118,1065,1134,1188,1207,1220,1163]},"region_attributes":{"Cervical spine":{"7":true}}}],"file_attributes":{}},"009-4.jpg308541":{"filename":"009-4.jpg","size":308541,"regions":[{"shape_attributes":{"name":"polygon","all_points_x":[832,737,812,921],"all_points_y":[248,334,433,377]},"region_attributes":{"Cervical spine":{"1":true}}},{"shape_attributes":{"name":"polygon","all_points_x":[689,814,713,662,601],"all_points_y":[376,451,539,494,485]},"region_attributes":{"Cervical spine":{"2":true}}},{"shape_attributes":{"name":"polygon","all_points_x":[613,708,654,593,536,590],"all_points_y":[510,550,657,625,624,518]},"region_attributes":{"Cervical spine":{"3":true}}},{"shape_attributes":{"name":"polygon","all_points_x":[536,653,625,557,491],"all_points_y":[656,673,785,760,772]},"region_attributes":{"Cervical spine":{"4":true}}},{"shape_attributes":{"name":"polygon","all_points_x":[501,614,611,491,489],"all_points_y":[803,798,896,904,848]},"region_attributes":{"Cervical spine":{"5":true}}},{"shape_attributes":{"name":"polygon","all_points_x":[489,608,622,549,491,499],"all_points_y":[953,926,1048,1057,1060,1004]},"region_attributes":{"Cervical spine":{"6":true}}},{"shape_attributes":{"name":"polygon","all_points_x":[497,629,651,536,523],"all_points_y":[1099,1057,1169,1211,1150]},"region_attributes":{"Cervical spine":{"7":true}}}],"file_attributes":{}},"010-3.jpg297631":{"filename":"010-3.jpg","size":297631,"regions":[{"shape_attributes":{"name":"polygon","all_points_x":[457,405,478,520],"all_points_y":[654,595,525,593]},"region_attributes":{"Cervical spine":{"1":true}}},{"shape_attributes":{"name":"polygon","all_points_x":[465,510,574,515],"all_points_y":[661,619,683,748]},"region_attributes":{"Cervical spine":{"2":true}}},{"shape_attributes":{"name":"polygon","all_points_x":[550,592,622,573],"all_points_y":[756,696,734,801]},"region_attributes":{"Cervical spine":{"3":true}}},{"shape_attributes":{"name":"polygon","all_points_x":[597,593,606,672,643],"all_points_y":[808,833,846,801,763]},"region_attributes":{"Cervical spine":{"4":true}}},{"shape_attributes":{"name":"polygon","all_points_x":[630,630,641,710,684],"all_points_y":[860,881,904,860,817]},"region_attributes":{"Cervical spine":{"5":true}}},{"shape_attributes":{"name":"polygon","all_points_x":[661,656,672,750,721],"all_points_y":[918,944,968,929,880]},"region_attributes":{"Cervical spine":{"6":true}}},{"shape_attributes":{"name":"polygon","all_points_x":[689,699,784,763],"all_points_y":[992,1033,998,944]},"region_attributes":{"Cervical spine":{"7":true}}}],"file_attributes":{}},"010-4.jpg330563":{"filename":"010-4.jpg","size":330563,"regions":[{"shape_attributes":{"name":"polygon","all_points_x":[635,553,637,699],"all_points_y":[491,558,606,561]},"region_attributes":{"Cervical spine":{"1":true}}},{"shape_attributes":{"name":"polygon","all_points_x":[565,614,576,504],"all_points_y":[571,601,670,641]},"region_attributes":{"Cervical spine":{"2":true}}},{"shape_attributes":{"name":"polygon","all_points_x":[483,462,542,561],"all_points_y":[681,715,729,688]},"region_attributes":{"Cervical spine":{"3":true}}},{"shape_attributes":{"name":"polygon","all_points_x":[461,453,528,533],"all_points_y":[766,798,798,756]},"region_attributes":{"Cervical spine":{"4":true}}},{"shape_attributes":{"name":"polygon","all_points_x":[462,459,539,523],"all_points_y":[843,878,859,817]},"region_attributes":{"Cervical spine":{"5":true}}},{"shape_attributes":{"name":"polygon","all_points_x":[477,475,555,539],"all_points_y":[916,961,923,884]},"region_attributes":{"Cervical spine":{"6":true}}},{"shape_attributes":{"name":"polygon","all_points_x":[505,526,592,565],"all_points_y":[993,1032,988,940]},"region_attributes":{"Cervical spine":{"7":true}}}],"file_attributes":{}},"011-2.jpg311349":{"filename":"011-2.jpg","size":311349,"regions":[{"shape_attributes":{"name":"polygon","all_points_x":[629,566,683,750],"all_points_y":[368,478,512,422]},"region_attributes":{"Cervical spine":{"1":true}}},{"shape_attributes":{"name":"polygon","all_points_x":[552,689,645,574,507,550],"all_points_y":[507,536,661,635,640,547]},"region_attributes":{"Cervical spine":{"2":true}}},{"shape_attributes":{"name":"polygon","all_points_x":[510,493,469,533,595,616],"all_points_y":[657,670,784,768,785,686]},"region_attributes":{"Cervical spine":{"3":true}}},{"shape_attributes":{"name":"polygon","all_points_x":[457,441,517,573,589],"all_points_y":[814,926,896,904,804]},"region_attributes":{"Cervical spine":{"4":true}}},{"shape_attributes":{"name":"polygon","all_points_x":[445,453,515,581,568,465],"all_points_y":[961,1060,1032,1030,928,945]},"region_attributes":{"Cervical spine":{"5":true}}},{"shape_attributes":{"name":"polygon","all_points_x":[469,565,616,465,459],"all_points_y":[1089,1051,1153,1201,1099]},"region_attributes":{"Cervical spine":{"6":true}}},{"shape_attributes":{"name":"polygon","all_points_x":[485,609,659,539],"all_points_y":[1230,1167,1278,1350]},"region_attributes":{"Cervical spine":{"7":true}}}],"file_attributes":{}},"011-3.jpg280143":{"filename":"011-3.jpg","size":280143,"regions":[{"shape_attributes":{"name":"polygon","all_points_x":[317,350,478,449],"all_points_y":[494,613,539,441]},"region_attributes":{"Cervical spine":{"1":true}}},{"shape_attributes":{"name":"polygon","all_points_x":[414,403,448,566,494],"all_points_y":[593,633,737,664,553]},"region_attributes":{"Cervical spine":{"2":true}}},{"shape_attributes":{"name":"polygon","all_points_x":[469,461,507,558,608,563],"all_points_y":[750,772,872,817,801,696]},"region_attributes":{"Cervical spine":{"3":true}}},{"shape_attributes":{"name":"polygon","all_points_x":[521,563,614,667,622],"all_points_y":[881,993,936,907,820]},"region_attributes":{"Cervical spine":{"4":true}}},{"shape_attributes":{"name":"polygon","all_points_x":[582,609,672,731,688,597],"all_points_y":[1001,1091,1049,1028,939,980]},"region_attributes":{"Cervical spine":{"5":true}}},{"shape_attributes":{"name":"polygon","all_points_x":[635,645,728,782,744],"all_points_y":[1112,1204,1179,1158,1059]},"region_attributes":{"Cervical spine":{"6":true}}},{"shape_attributes":{"name":"polygon","all_points_x":[665,657,680,817,792],"all_points_y":[1220,1236,1348,1307,1187]},"region_attributes":{"Cervical spine":{"7":true}}}],"file_attributes":{}},"013-3.jpg294282":{"filename":"013-3.jpg","size":294282,"regions":[{"shape_attributes":{"name":"polygon","all_points_x":[456,486,597,566],"all_points_y":[262,378,337,221]},"region_attributes":{"Cervical spine":{"1":true}}},{"shape_attributes":{"name":"polygon","all_points_x":[461,581,611,539,499],"all_points_y":[410,388,499,517,559]},"region_attributes":{"Cervical spine":{"2":true}}},{"shape_attributes":{"name":"polygon","all_points_x":[511,619,665,539],"all_points_y":[587,532,640,701]},"region_attributes":{"Cervical spine":{"3":true}}},{"shape_attributes":{"name":"polygon","all_points_x":[552,657,679,578,546],"all_points_y":[713,669,779,795,732]},"region_attributes":{"Cervical spine":{"4":true}}},{"shape_attributes":{"name":"polygon","all_points_x":[580,681,725,641,581],"all_points_y":[851,830,912,927,959]},"region_attributes":{"Cervical spine":{"5":true}}},{"shape_attributes":{"name":"polygon","all_points_x":[597,713,735,675,611,596,587],"all_points_y":[971,936,1047,1046,1079,1070,987]},"region_attributes":{"Cervical spine":{"6":true}}},{"shape_attributes":{"name":"polygon","all_points_x":[616,741,780,644],"all_points_y":[1110,1065,1179,1226]},"region_attributes":{"Cervical spine":{"7":true}}}],"file_attributes":{}},"013-4.jpg304410":{"filename":"013-4.jpg","size":304410,"regions":[{"shape_attributes":{"name":"polygon","all_points_x":[845,756,857,952],"all_points_y":[208,272,382,305]},"region_attributes":{"Cervical spine":{"1":true}}},{"shape_attributes":{"name":"polygon","all_points_x":[720,833,791,710,659],"all_points_y":[331,379,498,469,464]},"region_attributes":{"Cervical spine":{"2":true}}},{"shape_attributes":{"name":"polygon","all_points_x":[649,778,754,674,622],"all_points_y":[502,513,633,614,621]},"region_attributes":{"Cervical spine":{"3":true}}},{"shape_attributes":{"name":"polygon","all_points_x":[615,742,697,609],"all_points_y":[644,644,772,739]},"region_attributes":{"Cervical spine":{"4":true}}},{"shape_attributes":{"name":"polygon","all_points_x":[596,710,723,631,570],"all_points_y":[785,801,889,880,886]},"region_attributes":{"Cervical spine":{"5":true}}},{"shape_attributes":{"name":"polygon","all_points_x":[565,713,700,608,558],"all_points_y":[915,908,1018,1009,1024]},"region_attributes":{"Cervical spine":{"6":true}}},{"shape_attributes":{"name":"polygon","all_points_x":[562,685,707,574],"all_points_y":[1062,1035,1154,1179]},"region_attributes":{"Cervical spine":{"7":true}}}],"file_attributes":{}},"015-3.jpg326771":{"filename":"015-3.jpg","size":326771,"regions":[{"shape_attributes":{"name":"polygon","all_points_x":[532,532,668,660],"all_points_y":[416,537,508,406]},"region_attributes":{"Cervical spine":{"1":true}}},{"shape_attributes":{"name":"polygon","all_points_x":[532,666,669,573,526],"all_points_y":[590,570,698,715,739]},"region_attributes":{"Cervical spine":{"2":true}}},{"shape_attributes":{"name":"polygon","all_points_x":[533,681,696,543],"all_points_y":[785,726,839,874]},"region_attributes":{"Cervical spine":{"3":true}}},{"shape_attributes":{"name":"polygon","all_points_x":[559,703,712,628,570],"all_points_y":[906,868,978,987,1009]},"region_attributes":{"Cervical spine":{"4":true}}},{"shape_attributes":{"name":"polygon","all_points_x":[580,627,704,728,593],"all_points_y":[1054,1022,1013,1103,1136]},"region_attributes":{"Cervical spine":{"5":true}}},{"shape_attributes":{"name":"polygon","all_points_x":[592,725,741,608],"all_points_y":[1173,1141,1243,1258]},"region_attributes":{"Cervical spine":{"6":true}}},{"shape_attributes":{"name":"polygon","all_points_x":[612,719,766,641],"all_points_y":[1305,1264,1368,1416]},"region_attributes":{"Cervical spine":{"7":true}}}],"file_attributes":{}},"015-4.jpg317790":{"filename":"015-4.jpg","size":317790,"regions":[{"shape_attributes":{"name":"polygon","all_points_x":[794,745,841,902],"all_points_y":[390,491,532,454]},"region_attributes":{"Cervical spine":{"1":true}}},{"shape_attributes":{"name":"polygon","all_points_x":[727,861,819,731,677],"all_points_y":[552,578,700,681,687]},"region_attributes":{"Cervical spine":{"2":true}}},{"shape_attributes":{"name":"polygon","all_points_x":[681,824,808,719,657],"all_points_y":[719,731,829,813,819]},"region_attributes":{"Cervical spine":{"3":true}}},{"shape_attributes":{"name":"polygon","all_points_x":[663,800,779,693,643],"all_points_y":[855,851,962,952,965]},"region_attributes":{"Cervical spine":{"4":true}}},{"shape_attributes":{"name":"polygon","all_points_x":[631,662,766,761,637],"all_points_y":[1009,996,997,1094,1101]},"region_attributes":{"Cervical spine":{"5":true}}},{"shape_attributes":{"name":"polygon","all_points_x":[640,760,750,622],"all_points_y":[1129,1129,1227,1211]},"region_attributes":{"Cervical spine":{"6":true}}},{"shape_attributes":{"name":"polygon","all_points_x":[615,738,748,611],"all_points_y":[1272,1252,1357,1388]},"region_attributes":{"Cervical spine":{"7":true}}}],"file_attributes":{}},"016-3.jpg264513":{"filename":"016-3.jpg","size":264513,"regions":[{"shape_attributes":{"name":"polygon","all_points_x":[256,297,403,363],"all_points_y":[540,611,543,467]},"region_attributes":{"Cervical spine":{"1":true}}},{"shape_attributes":{"name":"polygon","all_points_x":[324,403,460,406,373],"all_points_y":[609,562,657,681,716]},"region_attributes":{"Cervical spine":{"2":true}}},{"shape_attributes":{"name":"polygon","all_points_x":[392,481,505,400],"all_points_y":[725,668,737,802]},"region_attributes":{"Cervical spine":{"3":true}}},{"shape_attributes":{"name":"polygon","all_points_x":[400,513,513,419],"all_points_y":[805,748,823,877]},"region_attributes":{"Cervical spine":{"4":true}}},{"shape_attributes":{"name":"polygon","all_points_x":[426,533,555,486,444],"all_points_y":[902,854,947,956,985]},"region_attributes":{"Cervical spine":{"5":true}}},{"shape_attributes":{"name":"polygon","all_points_x":[466,567,583,520,488],"all_points_y":[997,952,1040,1057,1076]},"region_attributes":{"Cervical spine":{"6":true}}},{"shape_attributes":{"name":"polygon","all_points_x":[510,595,628,532],"all_points_y":[1094,1065,1148,1192]},"region_attributes":{"Cervical spine":{"7":true}}}],"file_attributes":{}},"016-4.jpg313523":{"filename":"016-4.jpg","size":313523,"regions":[{"shape_attributes":{"name":"polygon","all_points_x":[663,627,728,757],"all_points_y":[444,534,564,501]},"region_attributes":{"Cervical spine":{"1":true}}},{"shape_attributes":{"name":"polygon","all_points_x":[630,719,675,619,574],"all_points_y":[549,580,687,655,644]},"region_attributes":{"Cervical spine":{"2":true}}},{"shape_attributes":{"name":"polygon","all_points_x":[548,657,628,514],"all_points_y":[666,700,780,731]},"region_attributes":{"Cervical spine":{"3":true}}},{"shape_attributes":{"name":"polygon","all_points_x":[508,618,573,485],"all_points_y":[731,786,836,780]},"region_attributes":{"Cervical spine":{"4":true}}},{"shape_attributes":{"name":"polygon","all_points_x":[464,561,523,464,414],"all_points_y":[821,848,939,903,901]},"region_attributes":{"Cervical spine":{"5":true}}},{"shape_attributes":{"name":"polygon","all_points_x":[411,518,489,439,388],"all_points_y":[927,946,1026,1007,1012]},"region_attributes":{"Cervical spine":{"6":true}}},{"shape_attributes":{"name":"polygon","all_points_x":[395,491,499,395],"all_points_y":[1047,1040,1135,1149]},"region_attributes":{"Cervical spine":{"7":true}}}],"file_attributes":{}},"017-3.jpg266582":{"filename":"017-3.jpg","size":266582,"regions":[{"shape_attributes":{"name":"polygon","all_points_x":[149,231,299,218],"all_points_y":[590,480,526,640]},"region_attributes":{"Cervical spine":{"1":true}}},{"shape_attributes":{"name":"polygon","all_points_x":[265,321,417,394,359],"all_points_y":[669,558,647,675,757]},"region_attributes":{"Cervical spine":{"2":true}}},{"shape_attributes":{"name":"polygon","all_points_x":[366,409,425,499,467,442],"all_points_y":[767,723,663,744,770,842]},"region_attributes":{"Cervical spine":{"3":true}}},{"shape_attributes":{"name":"polygon","all_points_x":[461,517,578,546,533],"all_points_y":[858,769,832,860,930]},"region_attributes":{"Cervical spine":{"4":true}}},{"shape_attributes":{"name":"polygon","all_points_x":[554,616,652,669,597],"all_points_y":[942,994,917,909,846]},"region_attributes":{"Cervical spine":{"5":true}}},{"shape_attributes":{"name":"polygon","all_points_x":[640,700,728,769,709,643],"all_points_y":[991,912,962,988,1073,1009]},"region_attributes":{"Cervical spine":{"6":true}}},{"shape_attributes":{"name":"polygon","all_points_x":[719,795,836,865,778],"all_points_y":[1076,1003,1062,1078,1163]},"region_attributes":{"Cervical spine":{"7":true}}}],"file_attributes":{}},"017-4.jpg335004":{"filename":"017-4.jpg","size":335004,"regions":[{"shape_attributes":{"name":"polygon","all_points_x":[776,691,780,830],"all_points_y":[417,483,552,504]},"region_attributes":{"Cervical spine":{"1":true}}},{"shape_attributes":{"name":"polygon","all_points_x":[672,766,690,663,580],"all_points_y":[539,596,684,666,631]},"region_attributes":{"Cervical spine":{"2":true}}},{"shape_attributes":{"name":"polygon","all_points_x":[561,511,595,618,668],"all_points_y":[657,745,759,780,707]},"region_attributes":{"Cervical spine":{"3":true}}},{"shape_attributes":{"name":"polygon","all_points_x":[493,461,534,567,599],"all_points_y":[775,871,862,883,801]},"region_attributes":{"Cervical spine":{"4":true}}},{"shape_attributes":{"name":"polygon","all_points_x":[455,464,529,564,554],"all_points_y":[927,1019,985,983,898]},"region_attributes":{"Cervical spine":{"5":true}}},{"shape_attributes":{"name":"polygon","all_points_x":[485,537,578,618,559],"all_points_y":[1060,1155,1100,1081,1004]},"region_attributes":{"Cervical spine":{"6":true}}},{"shape_attributes":{"name":"polygon","all_points_x":[551,619,704,625],"all_points_y":[1171,1258,1166,1098]},"region_attributes":{"Cervical spine":{"7":true}}}],"file_attributes":{}},"018-3.jpg439747":{"filename":"018-3.jpg","size":439747,"regions":[{"shape_attributes":{"name":"polygon","all_points_x":[561,586,660,649],"all_points_y":[690,745,710,662]},"region_attributes":{"Cervical spine":{"1":true}}},{"shape_attributes":{"name":"polygon","all_points_x":[628,687,716,659],"all_points_y":[756,706,747,789]},"region_attributes":{"Cervical spine":{"2":true}}},{"shape_attributes":{"name":"polygon","all_points_x":[674,724,744,694],"all_points_y":[795,749,788,832]},"region_attributes":{"Cervical spine":{"3":true}}},{"shape_attributes":{"name":"polygon","all_points_x":[712,760,787,731],"all_points_y":[837,804,834,877]},"region_attributes":{"Cervical spine":{"4":true}}},{"shape_attributes":{"name":"polygon","all_points_x":[742,763,816,798],"all_points_y":[899,924,886,845]},"region_attributes":{"Cervical spine":{"5":true}}},{"shape_attributes":{"name":"polygon","all_points_x":[777,833,857,807],"all_points_y":[946,891,927,977]},"region_attributes":{"Cervical spine":{"6":true}}},{"shape_attributes":{"name":"polygon","all_points_x":[874,827,850,900],"all_points_y":[943,981,1017,976]},"region_attributes":{"Cervical spine":{"7":true}}}],"file_attributes":{}},"018-4.jpg341573":{"filename":"018-4.jpg","size":341573,"regions":[{"shape_attributes":{"name":"polygon","all_points_x":[625,605,671,693],"all_points_y":[616,655,704,662]},"region_attributes":{"Cervical spine":{"1":true}}},{"shape_attributes":{"name":"polygon","all_points_x":[580,637,646,597],"all_points_y":[712,738,694,666]},"region_attributes":{"Cervical spine":{"2":true}}},{"shape_attributes":{"name":"polygon","all_points_x":[578,564,618,628],"all_points_y":[728,775,792,748]},"region_attributes":{"Cervical spine":{"3":true}}},{"shape_attributes":{"name":"polygon","all_points_x":[564,552,615,624],"all_points_y":[810,839,845,813]},"region_attributes":{"Cervical spine":{"4":true}}},{"shape_attributes":{"name":"polygon","all_points_x":[554,554,618,621],"all_points_y":[880,921,904,873]},"region_attributes":{"Cervical spine":{"5":true}}},{"shape_attributes":{"name":"polygon","all_points_x":[567,634,646,577],"all_points_y":[941,927,963,980]},"region_attributes":{"Cervical spine":{"6":true}}},{"shape_attributes":{"name":"polygon","all_points_x":[584,589,660,644],"all_points_y":[991,1044,1015,983]},"region_attributes":{"Cervical spine":{"7":true}}}],"file_attributes":{}},"019-3.jpg285421":{"filename":"019-3.jpg","size":285421,"regions":[{"shape_attributes":{"name":"polygon","all_points_x":[652,586,687,772],"all_points_y":[290,392,448,373]},"region_attributes":{"Cervical spine":{"1":true}}},{"shape_attributes":{"name":"polygon","all_points_x":[546,663,606,567,501],"all_points_y":[414,470,590,565,589]},"region_attributes":{"Cervical spine":{"2":true}}},{"shape_attributes":{"name":"polygon","all_points_x":[495,597,581,523,476],"all_points_y":[616,603,700,691,716]},"region_attributes":{"Cervical spine":{"3":true}}},{"shape_attributes":{"name":"polygon","all_points_x":[474,577,595,529,492],"all_points_y":[754,726,829,836,865]},"region_attributes":{"Cervical spine":{"4":true}}},{"shape_attributes":{"name":"polygon","all_points_x":[491,590,614,518],"all_points_y":[901,848,931,981]},"region_attributes":{"Cervical spine":{"5":true}}},{"shape_attributes":{"name":"polygon","all_points_x":[517,619,633,527],"all_points_y":[1009,955,1054,1101]},"region_attributes":{"Cervical spine":{"6":true}}},{"shape_attributes":{"name":"polygon","all_points_x":[532,646,656,539,539],"all_points_y":[1123,1084,1188,1227,1177]},"region_attributes":{"Cervical spine":{"7":true}}}],"file_attributes":{}},"019-4.jpg281366":{"filename":"019-4.jpg","size":281366,"regions":[{"shape_attributes":{"name":"polygon","all_points_x":[198,286,368,286],"all_points_y":[578,657,561,464]},"region_attributes":{"Cervical spine":{"1":true}}},{"shape_attributes":{"name":"polygon","all_points_x":[309,451,452,483,382],"all_points_y":[693,792,725,690,605]},"region_attributes":{"Cervical spine":{"2":true}}},{"shape_attributes":{"name":"polygon","all_points_x":[474,549,558,586,507],"all_points_y":[795,860,791,754,701]},"region_attributes":{"Cervical spine":{"3":true}}},{"shape_attributes":{"name":"polygon","all_points_x":[575,584,657,663,704,619],"all_points_y":[851,881,928,868,835,775]},"region_attributes":{"Cervical spine":{"4":true}}},{"shape_attributes":{"name":"polygon","all_points_x":[672,728,795,734],"all_points_y":[927,993,920,854]},"region_attributes":{"Cervical spine":{"5":true}}},{"shape_attributes":{"name":"polygon","all_points_x":[738,778,824,868,801],"all_points_y":[1000,1104,1048,1012,942]},"region_attributes":{"Cervical spine":{"6":true}}},{"shape_attributes":{"name":"polygon","all_points_x":[795,830,892,936,883],"all_points_y":[1113,1211,1155,1135,1048]},"region_attributes":{"Cervical spine":{"7":true}}}],"file_attributes":{}},"020-3.jpg288327":{"filename":"020-3.jpg","size":288327,"regions":[{"shape_attributes":{"name":"polygon","all_points_x":[233,253,365,343],"all_points_y":[327,417,375,293]},"region_attributes":{"Cervical spine":{"1":true}}},{"shape_attributes":{"name":"polygon","all_points_x":[247,354,391,341,294],"all_points_y":[458,409,529,540,587]},"region_attributes":{"Cervical spine":{"2":true}}},{"shape_attributes":{"name":"polygon","all_points_x":[303,409,433,372,343],"all_points_y":[605,555,637,663,696]},"region_attributes":{"Cervical spine":{"3":true}}},{"shape_attributes":{"name":"polygon","all_points_x":[356,447,488,433,407],"all_points_y":[710,657,734,761,804]},"region_attributes":{"Cervical spine":{"4":true}}},{"shape_attributes":{"name":"polygon","all_points_x":[428,485,526,561,502],"all_points_y":[819,898,842,820,747]},"region_attributes":{"Cervical spine":{"5":true}}},{"shape_attributes":{"name":"polygon","all_points_x":[504,556,611,646,584],"all_points_y":[912,991,924,912,841]},"region_attributes":{"Cervical spine":{"6":true}}},{"shape_attributes":{"name":"polygon","all_points_x":[577,643,731,668],"all_points_y":[1009,1091,1007,931]},"region_attributes":{"Cervical spine":{"7":true}}}],"file_attributes":{}},"020-4.jpg321975":{"filename":"020-4.jpg","size":321975,"regions":[{"shape_attributes":{"name":"polygon","all_points_x":[708,630,695,769],"all_points_y":[409,474,543,492]},"region_attributes":{"Cervical spine":{"1":true}}},{"shape_attributes":{"name":"polygon","all_points_x":[584,671,600,556,499],"all_points_y":[495,540,649,614,603]},"region_attributes":{"Cervical spine":{"2":true}}},{"shape_attributes":{"name":"polygon","all_points_x":[471,439,510,546,580],"all_points_y":[633,723,725,744,657]},"region_attributes":{"Cervical spine":{"3":true}}},{"shape_attributes":{"name":"polygon","all_points_x":[433,428,492,532,540],"all_points_y":[754,862,838,849,757]},"region_attributes":{"Cervical spine":{"4":true}}},{"shape_attributes":{"name":"polygon","all_points_x":[426,532,533,554,514,447],"all_points_y":[887,860,912,956,958,988]},"region_attributes":{"Cervical spine":{"5":true}}},{"shape_attributes":{"name":"polygon","all_points_x":[458,499,568,600,556],"all_points_y":[1019,1111,1065,1056,974]},"region_attributes":{"Cervical spine":{"6":true}}},{"shape_attributes":{"name":"polygon","all_points_x":[523,568,663,611],"all_points_y":[1145,1211,1147,1066]},"region_attributes":{"Cervical spine":{"7":true}}}],"file_attributes":{}}}